sougou/__init__.py
sougou/sougou.py
sougou_cli-1.0.0.dist-info/LICENSE
sougou_cli-1.0.0.dist-info/METADATA
sougou_cli-1.0.0.dist-info/WHEEL
sougou_cli-1.0.0.dist-info/entry_points.txt
sougou_cli-1.0.0.dist-info/top_level.txt
sougou_cli-1.0.0.dist-info/RECORD
