Metadata-Version: 2.1
Name: sougou-cli
Version: 1.0.0
Summary: a simple command line translation tool based on sougou api 
Home-page: https://github.com/Gaterny/sougou-cli
Author: Gaterny
Author-email: scusong@foxmail.com
License: MIT
Platform: all
Classifier: Programming Language :: Python :: 3
Classifier: License :: OSI Approved :: MIT License
Requires-Dist: requests
